LICENSE
MANIFEST.in
README.md
setup.py
graffiti/__init__.py
graffiti/core.py
graffiti/util.py
graffiti/visualize.py
graffiti.egg-info/PKG-INFO
graffiti.egg-info/SOURCES.txt
graffiti.egg-info/dependency_links.txt
graffiti.egg-info/not-zip-safe
graffiti.egg-info/top_level.txt
tests/__init__.py
tests/core_tests.py
tests/util_tests.py