Metadata-Version: 1.1
Name: graffiti
Version: 0.1.2
Summary: A library for declarative computation.
Home-page: https://github.com/SegFaultAX/graffiti
Author: Michael-Keith Bernard
Author-email: mkbernard.dev@gmail.com
License: MIT
Platform: any
Classifier: Development Status :: 3 - Alpha
Classifier: Intended Audience :: Developers
Classifier: Intended Audience :: Science/Research
Classifier: License :: OSI Approved :: MIT License
Classifier: Programming Language :: Python
Classifier: Topic :: Software Development :: Libraries
